torchbenchx/__init__.py
torchbenchx/benchx.py
torchbenchx-0.1.0.dist-info/licenses/LICENSE
torchbenchx-0.1.0.dist-info/METADATA
torchbenchx-0.1.0.dist-info/WHEEL
torchbenchx-0.1.0.dist-info/top_level.txt
torchbenchx-0.1.0.dist-info/RECORD
