Metadata-Version: 2.4
Name: torchbenchx
Version: 0.1.0
Summary: Unified Deep Learning Benchmark Library for PyTorch and TensorFlow
Home-page: https://github.com/syeedsaquib/torchbenchx
Author: Syeed Mohd Saquib
Author-email: Syeed Mohd Saquib <syeed.saquib@example.com>
License: MIT
Project-URL: Homepage, https://pypi.org/project/torchbenchx/
Project-URL: Repository, https://github.com/syeedsaquib/torchbenchx
Requires-Python: >=3.8
License-File: LICENSE
Requires-Dist: torch>=2.0
Requires-Dist: tensorflow>=2.12
Requires-Dist: plotly
Requires-Dist: pandas
Requires-Dist: numpy
Requires-Dist: psutil
Dynamic: author
Dynamic: home-page
Dynamic: license-file
Dynamic: requires-python
